Workbook

Sheet Comece aqui
A1: Ferramentas · Primeiras Vendas na Prática
A3: COMO USAR ESTA PLANILHA
A4: Células em bege são para você preencher. Células em azul-claro fazem as contas sozinhas: não digite nelas.
A5: Siga as abas da esquerda para a direita, na mesma ordem dos módulos do guia:
A6: 1. Ponto de partida (Módulo 1) · 2. Matriz de ideias (Módulo 2) · 3. Ficha de oferta (Módulo 3) · 4. Registro de contatos (Módulos 4 e 6) · 5. Plano de 7 dias (Módulo 7) · 6. Revisão semanal (Módulo 7).
A7: Funciona no Excel e no Google Planilhas (Arquivo > Importar). Se usar no celular, prefira o app do Google Planilhas.
A8: Os exemplos do guia são simulações. Os números desta planilha são os seus: nenhum resultado vem preenchido.

Sheet Ponto de partida
A1: Ponto de partida
A2: Módulo 1. Seja conservador: anote o que você tem de verdade hoje.
A4: Campo | B4: Sua resposta | C4: Dica
A5: Data de início do plano | C5: Use o formato dd/mm/aaaa. A revisão semanal conta as semanas a partir daqui.
A6: Minutos por dia disponíveis | C6: Número. Ex.: 45
A7: Habilidades que já uso | C7: O que fazem você ser chamado para ajudar
A8: Acessos (grupos, profissão, bairro, contatos) | C8: Onde estão pessoas que posso alcançar
A9: Dinheiro que aceito perder num teste (R$) | C9: Pode ser zero
A10: Restrições | C10: Horários, não aparecer em vídeo, não receber em casa...
A11: O tipo de venda mais fácil de testar primeiro parece ser... | C11: Sua intuição agora; o Módulo 2 testa

Sheet Matriz de ideias
A1: Matriz de ideias
A2: Módulo 2. Notas de 1 (ruim) a 5 (ótimo). Toda nota 4 ou 5 precisa de uma evidência; sem evidência, a nota máxima é 3.
A4: Critério | B4: Peso | C4: Ideia A: nota | D4: Evidência A | E4: Ideia B: nota | F4: Evidência B | G4: Ideia C: nota | H4: Evidência C
A5: Nome da ideia
A6: Demanda | B6: 3
A7: Margem | B7: 2
A8: Concorrência | B8: 2
A9: Dificuldade operacional | B9: 2
A10: Investimento inicial | B10: 1
A11: Total (máx. 50) | C11: =SUMPRODUCT($B$6:$B$10,C6:C10) | E11: =SUMPRODUCT($B$6:$B$10,E6:E10) | G11: =SUMPRODUCT($B$6:$B$10,G6:G10)
A12: Decisão | C12: =IF(COUNT(C6:C10)<5,"Preencha as 5 notas",IF(AND(C11>=35,COUNTIF(C6:C10,1)=0),"Testar","Reformular ou descartar")) | E12: =IF(COUNT(E6:E10)<5,"Preencha as 5 notas",IF(AND(E11>=35,COUNTIF(E6:E10,1)=0),"Testar","Reformular ou descartar")) | G12: =IF(COUNT(G6:G10)<5,"Preencha as 5 notas",IF(AND(G11>=35,COUNTIF(G6:G10,1)=0),"Testar","Reformular ou descartar"))
A14: Regra: testar se o total for 35 ou mais e nenhum critério tiver nota 1. Se duas ideias passarem, comece pela de maior demanda.

Sheet Ficha de oferta
A1: Ficha de oferta
A2: Módulo 3. Responda às nove perguntas e calcule o preço mínimo.
A4: Pergunta | B4: Sua resposta
A5: O que é
A6: Para quem (por situação)
A7: Resolve o quê
A8: O que a pessoa recebe
A9: Como funciona
A10: Prazo
A11: Preço e pagamento
A12: Garantia ou condições
A13: Próximo passo
A15: Cálculo do preço mínimo | B15: Valor
A16: Custo direto por venda (R$)
A17: Horas por entrega
A18: Valor da sua hora (R$)
A19: Custo do tempo (R$) | B19: =B17*B18
A20: Taxa fixa do meio de pagamento (R$)
A21: Taxa percentual do meio de pagamento (%)
A22: Preço mínimo (R$) | B22: =IFERROR((B16+B19+B20)/(1-B21),"")
A23: Preço que você vai cobrar (R$)
A24: Sobra por venda depois de custos e taxas (R$) | B24: =IF(B23="","",B23-B16-B20-B23*B21)
A25: Situação | B25: =IF(B23="","Informe o preço",IF(B23<B22,"Abaixo do mínimo: revise","Acima do mínimo"))
A27: A sobra inclui o pagamento do seu tempo dentro do preço. Taxas de plataformas mudam: confira a tabela atual no site oficial.

Sheet Registro de contatos
A1: Registro de contatos
A2: Módulos 4, 6 e 7. Uma linha por pessoa. Marque Sim conforme ela avança. A coluna Semana é calculada a partir da data de início.
A4: Data do contato | B4: Semana | C4: Nome | D4: Canal | E4: Sinal de interesse | F4: Respondeu? | G4: Conversa com diagnóstico? | H4: Proposta? | I4: Venda? | J4: Valor da venda (R$) | K4: Próxima ação | L4: Observação
B5: =IF(OR(A5="",'Ponto de partida'!$B$5=""),"",INT((A5-'Ponto de partida'!$B$5)/7)+1)
B6: =IF(OR(A6="",'Ponto de partida'!$B$5=""),"",INT((A6-'Ponto de partida'!$B$5)/7)+1)
B7: =IF(OR(A7="",'Ponto de partida'!$B$5=""),"",INT((A7-'Ponto de partida'!$B$5)/7)+1)
B8: =IF(OR(A8="",'Ponto de partida'!$B$5=""),"",INT((A8-'Ponto de partida'!$B$5)/7)+1)
B9: =IF(OR(A9="",'Ponto de partida'!$B$5=""),"",INT((A9-'Ponto de partida'!$B$5)/7)+1)
B10: =IF(OR(A10="",'Ponto de partida'!$B$5=""),"",INT((A10-'Ponto de partida'!$B$5)/7)+1)
B11: =IF(OR(A11="",'Ponto de partida'!$B$5=""),"",INT((A11-'Ponto de partida'!$B$5)/7)+1)
B12: =IF(OR(A12="",'Ponto de partida'!$B$5=""),"",INT((A12-'Ponto de partida'!$B$5)/7)+1)
B13: =IF(OR(A13="",'Ponto de partida'!$B$5=""),"",INT((A13-'Ponto de partida'!$B$5)/7)+1)
B14: =IF(OR(A14="",'Ponto de partida'!$B$5=""),"",INT((A14-'Ponto de partida'!$B$5)/7)+1)
B15: =IF(OR(A15="",'Ponto de partida'!$B$5=""),"",INT((A15-'Ponto de partida'!$B$5)/7)+1)
B16: =IF(OR(A16="",'Ponto de partida'!$B$5=""),"",INT((A16-'Ponto de partida'!$B$5)/7)+1)
... B204: =IF(OR(A204="",'Ponto de partida'!$B$5=""),"",INT((A204-'Ponto de partida'!$B$5)/7)+1)

Sheet Plano de 7 dias
A1: Plano de 7 dias
A2: Módulo 7. Marque o status de cada dia. Se atrasar, continue de onde parou.
A4: Dia | B4: Tarefas | C4: Pronto quando | D4: Status | E4: Anotações
A5: 1 | B5: Ponto de partida, lista de 20 problemas, 3 ideias | C5: Aba Ponto de partida completa e 3 ideias escritas | D5: A fazer
A6: 2 | B6: Matriz com evidências, ideia escolhida, método de validação | C6: Uma ideia com 35+ pontos e método escolhido | D6: A fazer
A7: 3 | B7: Oferta em uma página, preço mínimo, teste de explicação | C7: Alguém de fora explicou a oferta corretamente | D7: A fazer
A8: 4 | B8: Lista de 30 potenciais clientes, mensagens adaptadas, 10 envios | C8: 10 mensagens enviadas e registradas | D8: A fazer
A9: 5 | B9: 2 conteúdos publicados, mais 10 envios, responder quem respondeu | C9: 2 conteúdos no ar e 20 mensagens no total | D9: A fazer
A10: 6 | B10: Diagnósticos e propostas, mais 10 envios, 1º acompanhamento | C10: Toda conversa aberta teve diagnóstico ou proposta | D10: A fazer
A11: 7 | B11: Revisão semanal e um ajuste escolhido | C11: Revisão preenchida e um único ajuste definido | D11: A fazer
A14: Dia | B14: Conteúdo planejado (Módulo 5) | C14: Função | D14: Status | E14: Gerou perguntas ou mensagens?
A15: 1 | C15: Educar | D15: A fazer
A16: 2 | C16: Demonstrar | D16: A fazer
A17: 3 | C17: Educar | D17: A fazer
A18: 4 | C18: Quebrar objeção | D18: A fazer
A19: 5 | C19: Demonstrar | D19: A fazer
A20: 6 | C20: Provar | D20: A fazer
A21: 7 | C21: Convidar | D21: A fazer

Sheet Revisão semanal
A1: Revisão semanal
A2: Módulo 7. Os números vêm do Registro de contatos. Com menos de 30 contatos na semana, trate as taxas como pista, não como prova.
A4: Semana | B4: Contatados | C4: Responderam | D4: Conversas | E4: Propostas | F4: Vendas | G4: Taxa de resposta | H4: Taxa de conversa | I4: Taxa de proposta | J4: Taxa de fechamento | K4: Etapa mais fraca
A5: 1 | B5: =COUNTIF('Registro de contatos'!$B$5:$B$204,A5) | C5: =COUNTIFS('Registro de contatos'!$B$5:$B$204,A5,'Registro de contatos'!$F$5:$F$204,"Sim") | D5: =COUNTIFS('Registro de contatos'!$B$5:$B$204,A5,'Registro de contatos'!$G$5:$G$204,"Sim") | E5: =COUNTIFS('Registro de contatos'!$B$5:$B$204,A5,'Registro de contatos'!$H$5:$H$204,"Sim") | F5: =COUNTIFS('Registro de contatos'!$B$5:$B$204,A5,'Registro de contatos'!$I$5:$I$204,"Sim") | G5: =IF(B5=0,"",C5/B5) | H5: =IF(C5=0,"",D5/C5) | I5: =IF(D5=0,"",E5/D5) | J5: =IF(E5=0,"",F5/E5) | K5: =IF(B5=0,"",IF(C5=0,"Resposta",IF(D5=0,"Conversa",IF(E5=0,"Proposta",IF(F5=0,"Fechamento",INDEX({"Resposta","Conversa","Proposta","Fechamento"},MATCH(MIN(G5:J5),G5:J5,0)))))))
A6: 2 | B6: =COUNTIF('Registro de contatos'!$B$5:$B$204,A6) | C6: =COUNTIFS('Registro de contatos'!$B$5:$B$204,A6,'Registro de contatos'!$F$5:$F$204,"Sim") | D6: =COUNTIFS('Registro de contatos'!$B$5:$B$204,A6,'Registro de contatos'!$G$5:$G$204,"Sim") | E6: =COUNTIFS('Registro de contatos'!$B$5:$B$204,A6,'Registro de contatos'!$H$5:$H$204,"Sim") | F6: =COUNTIFS('Registro de contatos'!$B$5:$B$204,A6,'Registro de contatos'!$I$5:$I$204,"Sim") | G6: =IF(B6=0,"",C6/B6) | H6: =IF(C6=0,"",D6/C6) | I6: =IF(D6=0,"",E6/D6) | J6: =IF(E6=0,"",F6/E6) | K6: =IF(B6=0,"",IF(C6=0,"Resposta",IF(D6=0,"Conversa",IF(E6=0,"Proposta",IF(F6=0,"Fechamento",INDEX({"Resposta","Conversa","Proposta","Fechamento"},MATCH(MIN(G6:J6),G6:J6,0)))))))
A7: 3 | B7: =COUNTIF('Registro de contatos'!$B$5:$B$204,A7) | C7: =COUNTIFS('Registro de contatos'!$B$5:$B$204,A7,'Registro de contatos'!$F$5:$F$204,"Sim") | D7: =COUNTIFS('Registro de contatos'!$B$5:$B$204,A7,'Registro de contatos'!$G$5:$G$204,"Sim") | E7: =COUNTIFS('Registro de contatos'!$B$5:$B$204,A7,'Registro de contatos'!$H$5:$H$204,"Sim") | F7: =COUNTIFS('Registro de contatos'!$B$5:$B$204,A7,'Registro de contatos'!$I$5:$I$204,"Sim") | G7: =IF(B7=0,"",C7/B7) | H7: =IF(C7=0,"",D7/C7) | I7: =IF(D7=0,"",E7/D7) | J7: =IF(E7=0,"",F7/E7) | K7: =IF(B7=0,"",IF(C7=0,"Resposta",IF(D7=0,"Conversa",IF(E7=0,"Proposta",IF(F7=0,"Fechamento",INDEX({"Resposta","Conversa","Proposta","Fechamento"},MATCH(MIN(G7:J7),G7:J7,0)))))))
A8: 4 | B8: =COUNTIF('Registro de contatos'!$B$5:$B$204,A8) | C8: =COUNTIFS('Registro de contatos'!$B$5:$B$204,A8,'Registro de contatos'!$F$5:$F$204,"Sim") | D8: =COUNTIFS('Registro de contatos'!$B$5:$B$204,A8,'Registro de contatos'!$G$5:$G$204,"Sim") | E8: =COUNTIFS('Registro de contatos'!$B$5:$B$204,A8,'Registro de contatos'!$H$5:$H$204,"Sim") | F8: =COUNTIFS('Registro de contatos'!$B$5:$B$204,A8,'Registro de contatos'!$I$5:$I$204,"Sim") | G8: =IF(B8=0,"",C8/B8) | H8: =IF(C8=0,"",D8/C8) | I8: =IF(D8=0,"",E8/D8) | J8: =IF(E8=0,"",F8/E8) | K8: =IF(B8=0,"",IF(C8=0,"Resposta",IF(D8=0,"Conversa",IF(E8=0,"Proposta",IF(F8=0,"Fechamento",INDEX({"Resposta","Conversa","Proposta","Fechamento"},MATCH(MIN(G8:J8),G8:J8,0)))))))
A9: 5 | B9: =COUNTIF('Registro de contatos'!$B$5:$B$204,A9) | C9: =COUNTIFS('Registro de contatos'!$B$5:$B$204,A9,'Registro de contatos'!$F$5:$F$204,"Sim") | D9: =COUNTIFS('Registro de contatos'!$B$5:$B$204,A9,'Registro de contatos'!$G$5:$G$204,"Sim") | E9: =COUNTIFS('Registro de contatos'!$B$5:$B$204,A9,'Registro de contatos'!$H$5:$H$204,"Sim") | F9: =COUNTIFS('Registro de contatos'!$B$5:$B$204,A9,'Registro de contatos'!$I$5:$I$204,"Sim") | G9: =IF(B9=0,"",C9/B9) | H9: =IF(C9=0,"",D9/C9) | I9: =IF(D9=0,"",E9/D9) | J9: =IF(E9=0,"",F9/E9) | K9: =IF(B9=0,"",IF(C9=0,"Resposta",IF(D9=0,"Conversa",IF(E9=0,"Proposta",IF(F9=0,"Fechamento",INDEX({"Resposta","Conversa","Proposta","Fechamento"},MATCH(MIN(G9:J9),G9:J9,0)))))))
A10: 6 | B10: =COUNTIF('Registro de contatos'!$B$5:$B$204,A10) | C10: =COUNTIFS('Registro de contatos'!$B$5:$B$204,A10,'Registro de contatos'!$F$5:$F$204,"Sim") | D10: =COUNTIFS('Registro de contatos'!$B$5:$B$204,A10,'Registro de contatos'!$G$5:$G$204,"Sim") | E10: =COUNTIFS('Registro de contatos'!$B$5:$B$204,A10,'Registro de contatos'!$H$5:$H$204,"Sim") | F10: =COUNTIFS('Registro de contatos'!$B$5:$B$204,A10,'Registro de contatos'!$I$5:$I$204,"Sim") | G10: =IF(B10=0,"",C10/B10) | H10: =IF(C10=0,"",D10/C10) | I10: =IF(D10=0,"",E10/D10) | J10: =IF(E10=0,"",F10/E10) | K10: =IF(B10=0,"",IF(C10=0,"Resposta",IF(D10=0,"Conversa",IF(E10=0,"Proposta",IF(F10=0,"Fechamento",INDEX({"Resposta","Conversa","Proposta","Fechamento"},MATCH(MIN(G10:J10),G10:J10,0)))))))
A11: 7 | B11: =COUNTIF('Registro de contatos'!$B$5:$B$204,A11) | C11: =COUNTIFS('Registro de contatos'!$B$5:$B$204,A11,'Registro de contatos'!$F$5:$F$204,"Sim") | D11: =COUNTIFS('Registro de contatos'!$B$5:$B$204,A11,'Registro de contatos'!$G$5:$G$204,"Sim") | E11: =COUNTIFS('Registro de contatos'!$B$5:$B$204,A11,'Registro de contatos'!$H$5:$H$204,"Sim") | F11: =COUNTIFS('Registro de contatos'!$B$5:$B$204,A11,'Registro de contatos'!$I$5:$I$204,"Sim") | G11: =IF(B11=0,"",C11/B11) | H11: =IF(C11=0,"",D11/C11) | I11: =IF(D11=0,"",E11/D11) | J11: =IF(E11=0,"",F11/E11) | K11: =IF(B11=0,"",IF(C11=0,"Resposta",IF(D11=0,"Conversa",IF(E11=0,"Proposta",IF(F11=0,"Fechamento",INDEX({"Resposta","Conversa","Proposta","Fechamento"},MATCH(MIN(G11:J11),G11:J11,0)))))))
A12: 8 | B12: =COUNTIF('Registro de contatos'!$B$5:$B$204,A12) | C12: =COUNTIFS('Registro de contatos'!$B$5:$B$204,A12,'Registro de contatos'!$F$5:$F$204,"Sim") | D12: =COUNTIFS('Registro de contatos'!$B$5:$B$204,A12,'Registro de contatos'!$G$5:$G$204,"Sim") | E12: =COUNTIFS('Registro de contatos'!$B$5:$B$204,A12,'Registro de contatos'!$H$5:$H$204,"Sim") | F12: =COUNTIFS('Registro de contatos'!$B$5:$B$204,A12,'Registro de contatos'!$I$5:$I$204,"Sim") | G12: =IF(B12=0,"",C12/B12) | H12: =IF(C12=0,"",D12/C12) | I12: =IF(D12=0,"",E12/D12) | J12: =IF(E12=0,"",F12/E12) | K12: =IF(B12=0,"",IF(C12=0,"Resposta",IF(D12=0,"Conversa",IF(E12=0,"Proposta",IF(F12=0,"Fechamento",INDEX({"Resposta","Conversa","Proposta","Fechamento"},MATCH(MIN(G12:J12),G12:J12,0)))))))
A15: Semana | B15: 3 frases literais de potenciais clientes | E15: Objeções repetidas | H15: Conteúdo que gerou mensagens | K15: Único ajuste da próxima semana
A16: 1
A17: 2
A18: 3
A19: 4
A20: 5
A21: 6
A22: 7
A23: 8
